paladium/__init__.py
paladium/faction.py
paladium/paladium.py
paladium/player.py
paladium/rank.py
paladium-1.0.7.dist-info/METADATA
paladium-1.0.7.dist-info/WHEEL
paladium-1.0.7.dist-info/RECORD
