Metadata-Version: 2.1
Name: paladium
Version: 1.0.7
Summary: Python library for Paladium API
Project-URL: Homepage, https://github.com/aureliancnx/PaladiumPy
Project-URL: Issues, https://github.com/aureliancnx/PaladiumPy/issues
Author-email: aureliancnx <aureliancnx@paladium-pvp.fr>
Classifier: Programming Language :: Python :: 3
Requires-Python: >=3.6
